{
  "date": "2026-02-27",
  "coins": [
    {
      "name": "Bitcoin",
      "symbol": "BTC",
      "price": 66095,
      "change_24h": -2.8222,
      "market_cap": 1321595805412,
      "volume": 46750404521
    },
    {
      "name": "Ethereum",
      "symbol": "ETH",
      "price": 1962.23,
      "change_24h": -4.51739,
      "market_cap": 236826192670,
      "volume": 23634776019
    },
    {
      "name": "Tether",
      "symbol": "USDT",
      "price": 1.0,
      "change_24h": -0.00392,
      "market_cap": 183545857171,
      "volume": 74944933981
    },
    {
      "name": "XRP",
      "symbol": "XRP",
      "price": 1.38,
      "change_24h": -3.68923,
      "market_cap": 84428548570,
      "volume": 3098415525
    },
    {
      "name": "BNB",
      "symbol": "BNB",
      "price": 614.49,
      "change_24h": -1.412,
      "market_cap": 83695866125,
      "volume": 2010907563
    },
    {
      "name": "USDC",
      "symbol": "USDC",
      "price": 0.999912,
      "change_24h": 0.00137,
      "market_cap": 75203148973,
      "volume": 4721889900
    },
    {
      "name": "Solana",
      "symbol": "SOL",
      "price": 83.55,
      "change_24h": -3.66237,
      "market_cap": 47483887019,
      "volume": 4051040173
    },
    {
      "name": "TRON",
      "symbol": "TRX",
      "price": 0.284195,
      "change_24h": -0.71022,
      "market_cap": 26914360987,
      "volume": 421111237
    },
    {
      "name": "Dogecoin",
      "symbol": "DOGE",
      "price": 0.095097,
      "change_24h": -3.3535,
      "market_cap": 16062900638,
      "volume": 1118655514
    },
    {
      "name": "Figure Heloc",
      "symbol": "FIGR_HELOC",
      "price": 1.017,
      "change_24h": -1.41427,
      "market_cap": 15693488766,
      "volume": 24213651
    }
  ]
}