{
  "date": "2026-02-28",
  "fear_greed": {
    "value": 11,
    "label": "Extreme Fear",
    "history": [
      11,
      13,
      11,
      11,
      8,
      5,
      9
    ]
  },
  "market_breadth": 0.74,
  "market_mood": "BULLISH",
  "trending": [
    "PENGU",
    "VVV",
    "PAXG",
    "BTC",
    "SOL",
    "HYPE",
    "ETH"
  ],
  "top_movers": [
    "HYPE +14.2%",
    "TAO +5.3%",
    "DOT +4.6%",
    "SOL +4.3%",
    "UNI +3.7%"
  ],
  "worst_movers": [
    "FIGR_HELOC -1.8%",
    "TON -0.4%",
    "CC -0.3%",
    "USD1 -0.2%",
    "TRX -0.2%"
  ]
}