{
  "date": "2026-03-01",
  "fear_greed": {
    "value": 14,
    "label": "Extreme Fear",
    "history": [
      14,
      11,
      13,
      11,
      11,
      8,
      5
    ]
  },
  "market_breadth": 0.68,
  "market_mood": "BULLISH",
  "trending": [
    "BTC",
    "GRASS",
    "PAXG",
    "PENGU",
    "HYPE",
    "ETH",
    "XAUT"
  ],
  "top_movers": [
    "HYPE +7.0%",
    "AAVE +5.8%",
    "ZEC +4.8%",
    "LINK +4.5%",
    "TAO +4.3%"
  ],
  "worst_movers": [
    "TON -2.5%",
    "CC -2.1%",
    "FIGR_HELOC -1.1%",
    "DOT -0.6%",
    "BCH -0.6%"
  ]
}